[
  {
    "id": 1,
    "title": {
      "EN_US": "Tools",
      "AR_IQ": "أدوات",
      "KUKA_KU": "ئامراز",
      "KUSA_KU": "ئامرازەکان"
    },
    "children": [
      {
        "id": 1,
        "titlePage": {
          "EN_US": "Border",
          "AR_IQ": "حدود",
          "KUKA_KU": "سنوور",
          "KUSA_KU": "سنوور"
        },
        "slug": "border"
      },
      {
        "id": 2,
        "titlePage": {
          "EN_US": "Border Radius",
          "AR_IQ": "نصف قطر الحد",
          "KUKA_KU": "چەوماندنا سنوورى",
          "KUSA_KU": "تیژڕەوی سنوور"
        },
        "slug": "border-radius"
      },
      {
        "id": 3,
        "titlePage": {
          "EN_US": "Gradient",
          "AR_IQ": "الانحدار",
          "KUKA_KU": "گرادێنت",
          "KUSA_KU": "گرادێنت"
        },
        "slug": "gradient"
      },
      {
        "id": 4,
        "titlePage": {
          "EN_US": "Text Shadow",
          "AR_IQ": "ظل النص",
          "KUKA_KU": "سیبەرا دەقى",
          "KUSA_KU": "سێبەری دەق"
        },
        "slug": "text-shadow"
      },
      {
        "id": 5,
        "titlePage": {
          "EN_US": "Box Shadow",
          "AR_IQ": "ظل الصندوق",
          "KUKA_KU": "سیبەرا سندوقى",
          "KUSA_KU": "سێبەری سندوق"
        },
        "slug": "box-shadow"
      },
      {
        "id": 6,
        "titlePage": {
          "EN_US": "Filter",
          "AR_IQ": "منقي",
          "KUKA_KU": "فلتەر",
          "KUSA_KU": "فلتەر"
        },
        "slug": "filter"
      },
      {
        "id": 7,
        "titlePage": {
          "EN_US": "RGB Color",
          "AR_IQ": "لون RGB",
          "KUKA_KU": "ڕەنگێ rgb",
          "KUSA_KU": "ڕەنگی rgb"
        },
        "slug": "rgb-color"
      },
      {
        "id": 8,
        "titlePage": {
          "EN_US": "Transform",
          "AR_IQ": "تحول",
          "KUKA_KU": "گوهڕین",
          "KUSA_KU": "گۆڕان"
        },
        "slug": "transform"
      },
      {
        "id": 9,
        "titlePage": {
          "EN_US": "Scrollbar",
          "AR_IQ": "تحول",
          "KUKA_KU": "گوهڕین",
          "KUSA_KU": "گۆڕان"
        },
        "slug": "scrollbar"
      },
      {
        "id": 10,
        "titlePage": {
          "EN_US": "3D Transform",
          "AR_IQ": "تحول",
          "KUKA_KU": "گوهڕین",
          "KUSA_KU": "گۆڕان"
        },
        "slug": "3d-transform"
      }
    ]
  },
  {
    "id": 2,
    "title": {
      "EN_US": "Others",
      "AR_IQ": "عناصر",
      "KUKA_KU": "پێکهات",
      "KUSA_KU": "پێکهاتەکان"
    },
    "children": [
      {
        "id": 1,
        "titlePage": {
          "EN_US": "Transitions",
          "AR_IQ": "الانتقالات",
          "KUKA_KU": "ڤەگوهاستن",
          "KUSA_KU": "گواستنەوەکان"
        },
        "slug": "transitions"
      },
      {
        "id": 3,
        "titlePage": {
          "EN_US": "Colors",
          "AR_IQ": "الألوان",
          "KUKA_KU": "ڕەنگەکان",
          "KUSA_KU": "ڕەنگەکان"
        },
        "slug": "colors"
      },
      {
        "id": 4,
        "titlePage": {
          "EN_US": "Gradients Colors",
          "AR_IQ": "التدرجات",
          "KUKA_KU": "گرادێنت",
          "KUSA_KU": "گرادێنتەکان"
        },
        "slug": "gradients-colors"
      },
      {
        "id": 5,
        "titlePage": {
          "EN_US": "Text",
          "AR_IQ": "نص",
          "KUKA_KU": "دەق",
          "KUSA_KU": "دەق"
        },
        "slug": "text"
      },
      {
        "id": 6,
        "titlePage": {
          "EN_US": "Buttons",
          "AR_IQ": "أزرار",
          "KUKA_KU": "دوگمە",
          "KUSA_KU": "دوگمە"
        },
        "slug": "buttons"
      },
      {
        "id": 6,
        "titlePage": {
          "EN_US": "Loader",
          "AR_IQ": "أزرار",
          "KUKA_KU": "دوگمە",
          "KUSA_KU": "دوگمە"
        },
        "slug": "loader-generator"
      },
      {
        "id": 7,
        "titlePage": {
          "EN_US": "Minifier",
          "AR_IQ": "المصغر",
          "KUKA_KU": "مینیفایەر",
          "KUSA_KU": "مینیفایەر"
        },
        "slug": "minifier"
      },
      {
        "id": 8,
        "titlePage": {
          "EN_US": "Meta Tag",
          "AR_IQ": "علامة متغيرة",
          "KUKA_KU": "مێتا تاگ",
          "KUSA_KU": "مێتا تاگ"
        },
        "slug": "meta"
      },
      {
        "id": 9,
        "titlePage": {
          "EN_US": "QR code",
          "AR_IQ": "رمز الاستجابة السريعة",
          "KUKA_KU": "کۆد QR",
          "KUSA_KU": "کۆد QR"
        },
        "slug": "qr-code-generator"
      }
    ]
  }
]
